otimages/Exceptions/DockerException.py
otimages/Exceptions/__init__.py
otimages/__init__.py
otimages/__main__.py
otimages/main.py
otimages/utils/AppworksGatewayImages.py
otimages/utils/AppworksImages.py
otimages/utils/CSAIImages.py
otimages/utils/ContainerImage.py
otimages/utils/ContainerImageList.py
otimages/utils/__init__.py
otimages/utils/helm.py
otimages/utils/xECMImages.py
otimages/utils/xECMMonImages.py
otimages-0.7.3.dist-info/METADATA
otimages-0.7.3.dist-info/WHEEL
otimages-0.7.3.dist-info/entry_points.txt
otimages-0.7.3.dist-info/RECORD
