Metadata-Version: 2.1
Name: otimages
Version: 0.7.3
Summary: Script to pull and push container images for Opentext Extended ECM
Author: Kai Gatzweiler
Author-email: kgatzweiler@opentext.com
Requires-Python: >=3.11,<4.0
Classifier: Programming Language :: Python :: 3
Classifier: Programming Language :: Python :: 3.11
Classifier: Programming Language :: Python :: 3.12
Classifier: Programming Language :: Python :: 3.13
Requires-Dist: docker (>=6.1.3,<7.0.0)
Requires-Dist: requests (>=2.31.0,<3.0.0)
Requires-Dist: typer[all] (>=0.9.0,<0.10.0)
